scapinspector
