Metadata-Version: 1.0
Name: scapinspector
Version: 1.0.8
Summary: SCAP tool for parsing scap datastreams, creating tailoring files and parsing report results
Home-page: https://github.com/chris17453/scapinspector/
Author: Charles Watkins
Author-email: charles@titandws.com
License: Creative Commons Attribution-Noncommercial-Share Alike license
Platform: UNKNOWN
